README.md
flask_ulid.py
setup.py
Flask_ULID.egg-info/PKG-INFO
Flask_ULID.egg-info/SOURCES.txt
Flask_ULID.egg-info/dependency_links.txt
Flask_ULID.egg-info/not-zip-safe
Flask_ULID.egg-info/requires.txt
Flask_ULID.egg-info/top_level.txt