Metadata-Version: 1.1
Name: Flask-ULID
Version: 0.1.1
Summary: URL conveter with ULID on Flask
Home-page: https://github.com/setomits/flask-ulid/
Author: Mitsuhiro Setoguchi
Author-email: setomits@gmail.com
License: MIT
Platform: any
Classifier: Environment :: Web Environment
Classifier: Intended Audience :: Developers
Classifier: License :: OSI Approved :: MIT License
Classifier: Operating System :: OS Independent
Classifier: Programming Language :: Python
Classifier: Topic :: Internet :: WWW/HTTP :: Dynamic Content
Classifier: Topic :: Software Development :: Libraries :: Python Modules
